HISTORY.rst
LICENSE
MANIFEST.in
README.rst
setup.py
ifbcloud/__init__.py
ifbcloud/ifbcloud.py
ifbcloud.egg-info/PKG-INFO
ifbcloud.egg-info/SOURCES.txt
ifbcloud.egg-info/dependency_links.txt
ifbcloud.egg-info/entry_points.txt
ifbcloud.egg-info/requires.txt
ifbcloud.egg-info/top_level.txt