Metadata-Version: 1.1
Name: ifbcloud
Version: 0.0.3
Summary: Commandline utility to start and stop instances on the french IFB cloud
Home-page: https://github.com/mvdbeek/ifbcloud
Author: Marius van den Beek
Author-email: m.vandenbeek@gmail.com
License: MIT
Keywords: IFB
Platform: UNKNOWN
Classifier: Development Status :: 5 - Production/Stable
Classifier: Intended Audience :: Developers
Classifier: Environment :: Console
Classifier: Operating System :: POSIX
Classifier: Topic :: Software Development
Classifier: Topic :: Software Development :: Testing
Classifier: Natural Language :: English
Classifier: Programming Language :: Python :: 2
Classifier: Programming Language :: Python :: 2.7
Classifier: Programming Language :: Python :: 3
